[
  {
    "id": 1,
    "title": "釜山现代美术馆",
    "category": "해운대구",
    "location": "釜山市海云台区APEC路58号",
    "hours": "10:00 – 18:00（周一闭馆）",
    "fee": "免费参观",
    "phone": "051-278-2345",
    "description": "代表釜山现代艺术的空间，展出国内外现代美术作品的常设及企划展。毗邻乙淑岛生态公园，可同时欣赏自然与艺术。",
    "imageUrl": ""
  },
  {
    "id": 2,
    "title": "F1963",
    "category": "수영구",
    "location": "釜山市水营区九乐路123号街20号",
    "hours": "10:00 – 19:00（全年无休）",
    "fee": "免费（部分展览收费）",
    "phone": "051-756-1963",
    "description": "由高丽制钢水营工厂改建而成的复合文化空间，配备图书馆、展览馆、咖啡厅和表演场等多种文化设施。",
    "imageUrl": ""
  },
  {
    "id": 3,
    "title": "釜山市立美术馆",
    "category": "해운대구",
    "location": "釜山市海云台区APEC路58号",
    "hours": "10:00 – 18:00（周一闭馆）",
    "fee": "成人 ₩1,000 / 青少年 ₩600",
    "phone": "051-744-2602",
    "description": "釜山代表性市立美术馆，收藏并展出近现代美术作品。运营多样的企划展和教育项目，是釜山美术文化的中心。",
    "imageUrl": ""
  },
  {
    "id": 4,
    "title": "高恩摄影美术馆",
    "category": "해운대구",
    "location": "釜山市海云台区海云台海边路264号",
    "hours": "10:00 – 18:00（周一闭馆）",
    "fee": "成人 ₩5,000 / 学生 ₩3,000",
    "phone": "051-746-0055",
    "description": "韩国首家摄影专门美术馆，展出国内外摄影家作品，是探索摄影艺术历史与现代趋势的空间。",
    "imageUrl": ""
  },
  {
    "id": 5,
    "title": "亚特美术馆釜山",
    "category": "영도구",
    "location": "釜山市影岛区海洋路301号街25号",
    "hours": "10:00 – 20:00（全年无休）",
    "fee": "成人 ₩17,000 / 儿童 ₩13,000",
    "phone": "1800-1467",
    "description": "利用光与声音打造大型互动展览的沉浸式媒体艺术空间，以自然为主题构建梦幻般的数字艺术世界。",
    "imageUrl": ""
  },
  {
    "id": 6,
    "title": "釜山近代历史馆",
    "category": "중구",
    "location": "釜山市中区大庁路104号",
    "hours": "09:00 – 18:00（周一闭馆）",
    "fee": "免费参观",
    "phone": "051-253-3845",
    "description": "记录釜山近代历史的博物馆，展出从开港期到现代的釜山历史与文化，活用旧东洋拓殖株式会社釜山支店建筑。",
    "imageUrl": ""
  },
  {
    "id": 7,
    "title": "民主公园",
    "category": "중구",
    "location": "釜山市中区民主公园街19号",
    "hours": "09:00 – 18:00（周一闭馆）",
    "fee": "免费参观",
    "phone": "051-790-7400",
    "description": "纪念釜山民主化运动历史的公园，由民主抗争纪念馆和户外公园构成，可体验和了解釜山民主化运动历史。",
    "imageUrl": ""
  },
  {
    "id": 8,
    "title": "金井文化会馆",
    "category": "금정구",
    "location": "釜山市金井区中央大路1777号",
    "hours": "09:00 – 18:00（周一闭馆）",
    "fee": "各展览价格不同",
    "phone": "051-519-5252",
    "description": "金井区代表性文化空间，运营展览、演出、教育等多种文化项目，定期举办发掘推介地方艺术家作品的企划展。",
    "imageUrl": ""
  }
]
